MANIFEST.in
README.txt
setup.py
MorphoTester/DNE.py
MorphoTester/Morpho.py
MorphoTester/OPC.py
MorphoTester/RFI.py
MorphoTester/__init__.py
MorphoTester/implicitfair.py
MorphoTester/normcore.py
MorphoTester/plython.py
MorphoTester/render.py
MorphoTester.egg-info/PKG-INFO
MorphoTester.egg-info/SOURCES.txt
MorphoTester.egg-info/dependency_links.txt
MorphoTester.egg-info/requires.txt
MorphoTester.egg-info/top_level.txt