Metadata-Version: 1.1
Name: MorphoTester
Version: 1.0.1
Summary: A scientific computing application for measuring topographic shape in 3D anatomical data.
Home-page: UNKNOWN
Author: Julia Winchester
Author-email: julia.winchester@stonybrook.edu
License: GPL
Platform: UNKNOWN
Classifier: Development Status :: 5 - Production/Stable
Classifier: Environment :: MacOS X
Classifier: Environment :: Win32 (MS Windows)
Classifier: Intended Audience :: Science/Research
Classifier: License :: OSI Approved :: GNU General Public License v2 or later (GPLv2+)
Classifier: Topic :: Scientific/Engineering :: Bio-Informatics
Classifier: Topic :: Scientific/Engineering :: Information Analysis
Classifier: Topic :: Scientific/Engineering :: Visualization
Classifier: Topic :: Multimedia :: Graphics :: 3D Rendering
